Metadata-Version: 2.1
Name: ifaa
Version: 0.1.0
Summary: Robust association identification and inference for absolute abundance in microbiome analyses
Home-page: https://github.com/lovestat/ifaa
Author: Zhigang Li, Quran Wu, Shangchen Song
Author-email: lzg2151@gmail.com, s.song@ufl.edu
License: MIT
Platform: UNKNOWN
Classifier: Programming Language :: Python
Classifier: Programming Language :: Python :: 3
License-File: LICENSE.txt
